{
  "_fv": 18,
  "_type": "recipe",
  "definition": {
    "recipeType": "Crafting",
    "xpReward": 0.0,
    "cookingTime": 200,
    "recipeRetstackSize": 1,
    "group": "cyberware2",
    "recipeShapeless": true,
    "recipeSlots": [
      {
        "value": "CUSTOM:ComponentChromePlating"
      },
      {
        "value": "CUSTOM:ComponentFiberOptics"
      },
      {
        "value": ""
      },
      {
        "value": "CUSTOM:ComponentSyntheticNerves"
      },
      {
        "value": "CUSTOM:ComponentFiberOptics"
      },
      {
        "value": ""
      },
      {
        "value": ""
      },
      {
        "value": ""
      },
      {
        "value": ""
      }
    ],
    "recipeReturnStack": {
      "value": "CUSTOM:NightVision"
    },
    "name": "night_vision_blueprint",
    "namespace": "mod"
  }
}